{
  "name": "habbo_orderinfo_dialog",
  "source": "sources\\win63_2026_crypted_version\\src\\layouts\\1608_habbo_orderinfo_dialog_xml$4472e2cffcf84930c0761d73590bbf7c1433101786.xml",
  "window": {
    "tag": "window",
    "typeId": -1,
    "attributes": {},
    "children": [
      {
        "tag": "container",
        "typeId": 4,
        "attributes": {
          "x": "0",
          "y": "0",
          "width": "284",
          "height": "149",
          "params": "131088",
          "style": "0",
          "name": "habbo_orderinfo_dialog"
        },
        "children": [
          {
            "tag": "border",
            "typeId": 30,
            "attributes": {
              "x": "0",
              "y": "0",
              "width": "284",
              "height": "149",
              "params": "131088",
              "style": "0"
            },
            "children": [
              {
                "tag": "itemlist_vertical",
                "typeId": 50,
                "attributes": {
                  "x": "0",
                  "y": "0",
                  "width": "284",
                  "height": "149",
                  "params": "131088",
                  "style": "3",
                  "name": "orderItemList"
                },
                "children": [
                  {
                    "tag": "container",
                    "typeId": 4,
                    "attributes": {
                      "x": "0",
                      "y": "0",
                      "width": "284",
                      "height": "80",
                      "params": "16",
                      "style": "0",
                      "name": "infoContainer"
                    },
                    "children": [
                      {
                        "tag": "text",
                        "typeId": 10,
                        "attributes": {
                          "x": "16",
                          "y": "14",
                          "width": "250",
                          "height": "15",
                          "params": "16",
                          "style": "3",
                          "name": "habbo_orderinfo_text_a",
                          "caption": "${catalog.purchase.confirmation.dialog.costs}"
                        },
                        "children": [],
                        "vars": {
                          "auto_size": "left",
                          "text_style": "u_small",
                          "mouse_wheel_enabled": false,
                          "multiline": true,
                          "word_wrap": true,
                          "spacing": 0,
                          "leading": 0
                        }
                      },
                      {
                        "tag": "text",
                        "typeId": 10,
                        "attributes": {
                          "x": "16",
                          "y": "34",
                          "width": "250",
                          "height": "15",
                          "params": "16",
                          "style": "3",
                          "name": "habbo_orderinfo_text_b",
                          "caption": "${catalog.purchase.confirmation.dialog.amount}"
                        },
                        "children": [],
                        "vars": {
                          "auto_size": "left",
                          "text_style": "u_small",
                          "mouse_wheel_enabled": false,
                          "multiline": true,
                          "word_wrap": true,
                          "spacing": 0,
                          "leading": 0
                        }
                      },
                      {
                        "tag": "text",
                        "typeId": 10,
                        "attributes": {
                          "x": "16",
                          "y": "54",
                          "width": "250",
                          "height": "26",
                          "params": "16",
                          "style": "3",
                          "name": "habbo_orderinfo_text_c",
                          "caption": "${catalog.purchase.confirmation.dialog.remaining}"
                        },
                        "children": [],
                        "vars": {
                          "auto_size": "left",
                          "text_style": "u_small",
                          "mouse_wheel_enabled": false,
                          "multiline": true,
                          "word_wrap": true,
                          "spacing": 0,
                          "leading": 0
                        }
                      }
                    ]
                  },
                  {
                    "tag": "container",
                    "typeId": 4,
                    "attributes": {
                      "x": "0",
                      "y": "80",
                      "width": "281",
                      "height": "34",
                      "params": "16",
                      "style": "0",
                      "name": "buttonContainer"
                    },
                    "children": [
                      {
                        "tag": "button",
                        "typeId": 60,
                        "attributes": {
                          "x": "151",
                          "y": "3",
                          "width": "56",
                          "height": "22",
                          "params": "393361",
                          "style": "3",
                          "name": "button_cancel",
                          "caption": "${generic.cancel}",
                          "width_max": "130"
                        },
                        "children": []
                      },
                      {
                        "tag": "button",
                        "typeId": 60,
                        "attributes": {
                          "x": "80",
                          "y": "3",
                          "width": "35",
                          "height": "22",
                          "params": "131217",
                          "style": "3",
                          "name": "button_ok",
                          "caption": "${generic.ok}",
                          "width_max": "130"
                        },
                        "children": []
                      }
                    ]
                  }
                ]
              }
            ]
          }
        ]
      }
    ]
  },
  "vars": {},
  "filters": [],
  "layoutWidth": 284,
  "layoutHeight": 149
}